stripe/__init__.py
stripe/_account.py
stripe/_account_capability_service.py
stripe/_account_external_account_service.py
stripe/_account_link.py
stripe/_account_link_service.py
stripe/_account_login_link_service.py
stripe/_account_person_service.py
stripe/_account_service.py
stripe/_account_session.py
stripe/_account_session_service.py
stripe/_any_iterator.py
stripe/_api_mode.py
stripe/_api_requestor.py
stripe/_api_resource.py
stripe/_api_version.py
stripe/_app_info.py
stripe/_apple_pay_domain.py
stripe/_apple_pay_domain_service.py
stripe/_application.py
stripe/_application_fee.py
stripe/_application_fee_refund.py
stripe/_application_fee_refund_service.py
stripe/_application_fee_service.py
stripe/_apps_service.py
stripe/_balance.py
stripe/_balance_service.py
stripe/_balance_transaction.py
stripe/_balance_transaction_service.py
stripe/_bank_account.py
stripe/_base_address.py
stripe/_billing_portal_service.py
stripe/_billing_service.py
stripe/_capability.py
stripe/_card.py
stripe/_cash_balance.py
stripe/_charge.py
stripe/_charge_service.py
stripe/_checkout_service.py
stripe/_client_options.py
stripe/_climate_service.py
stripe/_confirmation_token.py
stripe/_confirmation_token_service.py
stripe/_connect_collection_transfer.py
stripe/_country_spec.py
stripe/_country_spec_service.py
stripe/_coupon.py
stripe/_coupon_service.py
stripe/_createable_api_resource.py
stripe/_credit_note.py
stripe/_credit_note_line_item.py
stripe/_credit_note_line_item_service.py
stripe/_credit_note_preview_lines_service.py
stripe/_credit_note_service.py
stripe/_custom_method.py
stripe/_customer.py
stripe/_customer_balance_transaction.py
stripe/_customer_balance_transaction_service.py
stripe/_customer_cash_balance_service.py
stripe/_customer_cash_balance_transaction.py
stripe/_customer_cash_balance_transaction_service.py
stripe/_customer_funding_instructions_service.py
stripe/_customer_payment_method_service.py
stripe/_customer_payment_source_service.py
stripe/_customer_service.py
stripe-12.0.0.dist-info/LICENSE
stripe-12.0.0.dist-info/METADATA
stripe-12.0.0.dist-info/WHEEL
stripe-12.0.0.dist-info/top_level.txt
stripe-12.0.0.dist-info/RECORD
