Metadata-Version: 2.1
Name: stripe
Version: 12.0.0
Summary: Python bindings for the Stripe API
Home-page: https://github.com/stripe/stripe-python
Author: Stripe
Author-email: support@stripe.com
License: MIT
Project-URL: Bug Tracker, https://github.com/stripe/stripe-python/issues
Project-URL: Changes, https://github.com/stripe/stripe-python/blob/master/CHANGELOG.md
Project-URL: Documentation, https://stripe.com/docs/api/?lang=python
Project-URL: Source Code, https://github.com/stripe/stripe-python
Keywords: stripe api payments
Classifier: Development Status :: 5 - Production/Stable
Classifier: Intended Audience :: Developers
Classifier: License :: OSI Approved :: MIT License
Classifier: Operating System :: OS Independent
Classifier: Programming Language :: Python
Classifier: Programming Language :: Python :: 3
Classifier: Programming Language :: Python :: 3 :: Only
Classifier: Programming Language :: Python :: 3.6
Classifier: Programming Language :: Python :: 3.7
Classifier: Programming Language :: Python :: 3.8
Classifier: Programming Language :: Python :: 3.9
Classifier: Programming Language :: Python :: 3.10
Classifier: Programming Language :: Python :: 3.11
Classifier: Programming Language :: Python :: 3.12
Classifier: Programming Language :: Python :: Implementation :: CPython
Classifier: Programming Language :: Python :: Implementation :: PyPy
Classifier: Topic :: Software Development :: Libraries :: Python Modules
Requires-Python: >=3.6
License-File: LICENSE
